juvini/__init__.py
juvini/juvini.py
juvini/data/iris.csv
juvini-1.0.8.dist-info/LICENSE
juvini-1.0.8.dist-info/METADATA
juvini-1.0.8.dist-info/WHEEL
juvini-1.0.8.dist-info/top_level.txt
juvini-1.0.8.dist-info/RECORD
