Metadata-Version: 2.1
Name: juvini
Version: 1.0.8
Summary: EDA for dummies
Home-page: https://github.com/niths4u/juvini
Author: Niths
Author-email: nitinmn@gmail.com
License: UNKNOWN
Platform: UNKNOWN
Classifier: Programming Language :: Python :: 3
Classifier: License :: OSI Approved :: MIT License
Classifier: Operating System :: OS Independent
Requires-Python: >=3.6
Requires-Dist: pandas
Requires-Dist: matplotlib
Requires-Dist: seaborn
